deviant.py
deviant-1.2.0.dist-info/WHEEL
deviant-1.2.0.dist-info/METADATA
deviant-1.2.0.dist-info/RECORD
