Metadata-Version: 2.1
Name: deviant
Version: 1.2.0
Summary: Модуль для работы с Deviant Api
Home-page: https://github.com/DarsoX/Deviant/wiki/Documentation-Deviant
Author: Deviant
Author-email: darsox.anime@gmail.com
Requires-Python: >=3.6,<4.0
Classifier: Programming Language :: Python :: 3
Classifier: Programming Language :: Python :: 3.6
Classifier: Programming Language :: Python :: 3.7
Classifier: Programming Language :: Python :: 3.8
Classifier: Programming Language :: Python :: 3.9
Project-URL: Repository, https://github.com/DarsoX/Deviant
